README.rst
setup.cfg
setup.py
juju_docean/__init__.py
juju_docean/cli.py
juju_docean/client.py
juju_docean/commands.py
juju_docean/config.py
juju_docean/constraints.py
juju_docean/env.py
juju_docean/exceptions.py
juju_docean/ops.py
juju_docean/provider.py
juju_docean/runner.py
juju_docean/ssh.py
juju_docean.egg-info/PKG-INFO
juju_docean.egg-info/SOURCES.txt
juju_docean.egg-info/dependency_links.txt
juju_docean.egg-info/entry_points.txt
juju_docean.egg-info/requires.txt
juju_docean.egg-info/top_level.txt
juju_docean/tests/__init__.py
juju_docean/tests/base.py
juju_docean/tests/test_commands.py
juju_docean/tests/test_config.py
juju_docean/tests/test_constraints.py
juju_docean/tests/test_environment.py
juju_docean/tests/test_exceptions.py
juju_docean/tests/test_runner.py