Metadata-Version: 1.1
Name: juju-docean
Version: 0.6.0
Summary: Digital Ocean integration with juju
Home-page: https://github.com/kapilt/juju-digitalocean
Author: Kapil Thangavelu
Author-email: kapil.foss@gmail.com
License: BSD
Platform: UNKNOWN
Classifier: Intended Audience :: Developers
Classifier: Programming Language :: Python
Classifier: Operating System :: OS Independent
